{
  "id": "277361003950505984",
  "tag": "Mailex#6538",
  "sharedServers": [
    {
      "id": "277371194422853633",
      "name": "Mailex' Twitch Server"
    },
    {
      "id": "405763731079823380",
      "name": "Danho's Dutch Discord"
    },
    {
      "id": "460926327269359626",
      "name": "Danho's Misc"
    }
  ],
  "replyPerson": null,
  "daily": {
    "lastClaim": null,
    "nextClaim": null,
    "streak": 0
  },
  "avatar": "https://cdn.discordapp.com/avatars/277361003950505984/4dc81ad57cee039c715e9c4dcdbe888b.webp",
  "playlists": []
}